{
  "docusaurus-plugin-content-docs": {
    "default": {
      "path": "/PivotHead/docs",
      "versions": [
        {
          "name": "current",
          "label": "Next",
          "isLast": true,
          "path": "/PivotHead/docs",
          "mainDocId": "introduction",
          "docs": [
            {
              "id": "contributors/code-of-conduct",
              "path": "/PivotHead/docs/contributors/code-of-conduct",
              "sidebar": "tutorialSidebar"
            },
            {
              "id": "contributors/contributors",
              "path": "/PivotHead/docs/contributors/",
              "sidebar": "tutorialSidebar"
            },
            {
              "id": "contributors/how-to-contribute",
              "path": "/PivotHead/docs/contributors/how-to-contribute",
              "sidebar": "tutorialSidebar"
            },
            {
              "id": "contributors/monorepo-setup",
              "path": "/PivotHead/docs/contributors/monorepo-setup",
              "sidebar": "tutorialSidebar"
            },
            {
              "id": "contributors/quick-start",
              "path": "/PivotHead/docs/contributors/quick-start",
              "sidebar": "tutorialSidebar"
            },
            {
              "id": "Installation",
              "path": "/PivotHead/docs/Installation",
              "sidebar": "tutorialSidebar"
            },
            {
              "id": "introduction",
              "path": "/PivotHead/docs/introduction",
              "sidebar": "tutorialSidebar"
            },
            {
              "id": "tutorial-basics/core/api-reference",
              "path": "/PivotHead/docs/tutorial-basics/core/api-reference",
              "sidebar": "tutorialSidebar"
            },
            {
              "id": "tutorial-basics/core/core-concepts",
              "path": "/PivotHead/docs/tutorial-basics/core/core-concepts",
              "sidebar": "tutorialSidebar"
            },
            {
              "id": "tutorial-basics/core/examples",
              "path": "/PivotHead/docs/tutorial-basics/core/examples",
              "sidebar": "tutorialSidebar"
            },
            {
              "id": "tutorial-basics/troubleshooting",
              "path": "/PivotHead/docs/tutorial-basics/troubleshooting",
              "sidebar": "tutorialSidebar"
            },
            {
              "id": "tutorial-basics/web-component",
              "path": "/PivotHead/docs/tutorial-basics/web-component",
              "sidebar": "tutorialSidebar"
            },
            {
              "id": "tutorial-basics/wrappers/react",
              "path": "/PivotHead/docs/tutorial-basics/wrappers/react",
              "sidebar": "tutorialSidebar"
            },
            {
              "id": "tutorial-basics/wrappers/vue",
              "path": "/PivotHead/docs/tutorial-basics/wrappers/vue",
              "sidebar": "tutorialSidebar"
            },
            {
              "id": "Why-we-use-pivothead",
              "path": "/PivotHead/docs/Why-we-use-pivothead",
              "sidebar": "tutorialSidebar"
            },
            {
              "id": "/category/tutorials",
              "path": "/PivotHead/docs/category/tutorials",
              "sidebar": "tutorialSidebar"
            },
            {
              "id": "/category/contribution-guide",
              "path": "/PivotHead/docs/category/contribution-guide",
              "sidebar": "tutorialSidebar"
            }
          ],
          "draftIds": [],
          "sidebars": {
            "tutorialSidebar": {
              "link": {
                "path": "/PivotHead/docs/introduction",
                "label": "introduction"
              }
            }
          }
        }
      ],
      "breadcrumbs": true
    }
  }
}
